eurydice/__init__.py
eurydice/client.py
eurydice/config.py
eurydice/exceptions.py
eurydice/types.py
eurydice/audio/__init__.py
eurydice/audio/decoder.py
eurydice/audio/formats.py
eurydice/audio/tokens.py
eurydice/cache/__init__.py
eurydice/cache/base.py
eurydice/cache/filesystem.py
eurydice/cache/key.py
eurydice/cache/memory.py
eurydice/providers/__init__.py
eurydice/providers/base.py
eurydice/providers/lmstudio.py
eurydice_tts-0.0.1.dist-info/METADATA
eurydice_tts-0.0.1.dist-info/WHEEL
eurydice_tts-0.0.1.dist-info/licenses/LICENSE
eurydice_tts-0.0.1.dist-info/RECORD
