Metadata-Version: 2.4
Name: eurydice-tts
Version: 0.0.1
Summary: Text-to-speech library bridging to Orpheus TTS model - bringing text to life
Project-URL: Homepage, https://github.com/mustafazidan/eurydice
Project-URL: Documentation, https://github.com/mustafazidan/eurydice#readme
Project-URL: Repository, https://github.com/mustafazidan/eurydice
Project-URL: Issues, https://github.com/mustafazidan/eurydice/issues
Project-URL: Changelog, https://github.com/mustafazidan/eurydice/blob/main/CHANGELOG.md
Author-email: Mustafa Abuelfadl <mustafa@zidan.me>
License-Expression: MIT
License-File: LICENSE
Keywords: ai,audio,eurydice,ml,orpheus,speech-synthesis,text-to-speech,tts
Classifier: Development Status :: 4 - Beta
Classifier: Intended Audience :: Developers
Classifier: License :: OSI Approved :: MIT License
Classifier: Programming Language :: Python :: 3
Classifier: Programming Language :: Python :: 3.10
Classifier: Programming Language :: Python :: 3.11
Classifier: Programming Language :: Python :: 3.12
Classifier: Programming Language :: Python :: 3.13
Classifier: Programming Language :: Python :: 3.14
Classifier: Topic :: Multimedia :: Sound/Audio :: Speech
Classifier: Topic :: Scientific/Engineering :: Artificial Intelligence
Classifier: Typing :: Typed
Requires-Python: >=3.10
Requires-Dist: httpx>=0.24.0
Provides-Extra: all
Requires-Dist: accelerate>=0.24.0; extra == 'all'
Requires-Dist: mkdocs-material>=9.5.0; extra == 'all'
Requires-Dist: mkdocs>=1.5.0; extra == 'all'
Requires-Dist: mkdocstrings[python]>=0.24.0; extra == 'all'
Requires-Dist: mypy>=1.7.0; extra == 'all'
Requires-Dist: numpy>=1.24.0; extra == 'all'
Requires-Dist: pytest-asyncio>=0.23.0; extra == 'all'
Requires-Dist: pytest-cov>=4.0.0; extra == 'all'
Requires-Dist: pytest>=8.0.0; extra == 'all'
Requires-Dist: ruff>=0.1.0; extra == 'all'
Requires-Dist: snac>=1.2.0; extra == 'all'
Requires-Dist: torch>=2.0.0; extra == 'all'
Requires-Dist: transformers>=4.35.0; extra == 'all'
Provides-Extra: audio
Requires-Dist: numpy>=1.24.0; extra == 'audio'
Requires-Dist: snac>=1.2.0; extra == 'audio'
Requires-Dist: torch>=2.0.0; extra == 'audio'
Provides-Extra: dev
Requires-Dist: mypy>=1.7.0; extra == 'dev'
Requires-Dist: pytest-asyncio>=0.23.0; extra == 'dev'
Requires-Dist: pytest-cov>=4.0.0; extra == 'dev'
Requires-Dist: pytest>=8.0.0; extra == 'dev'
Requires-Dist: ruff>=0.1.0; extra == 'dev'
Provides-Extra: docs
Requires-Dist: mkdocs-material>=9.5.0; extra == 'docs'
Requires-Dist: mkdocs>=1.5.0; extra == 'docs'
Requires-Dist: mkdocstrings[python]>=0.24.0; extra == 'docs'
Provides-Extra: embedded
Requires-Dist: accelerate>=0.24.0; extra == 'embedded'
Requires-Dist: numpy>=1.24.0; extra == 'embedded'
Requires-Dist: snac>=1.2.0; extra == 'embedded'
Requires-Dist: torch>=2.0.0; extra == 'embedded'
Requires-Dist: transformers>=4.35.0; extra == 'embedded'
